{
  "version": "1.1",
  "meta": {
    "title": "Forward Propagation Explained",
    "resolution": [
      1920,
      1080
    ],
    "fps": 30,
    "theme": "modern",
    "show_subtitles": true,
    "pacing": "educational",
    "continuity": true,
    "continuity_duration": "1.3s",
    "glow_release_padding": "1.4s"
  },
  "objects": [
    {
      "type": "group",
      "id": "steps",
      "position": "bottom",
      "children": [
        {
          "type": "token",
          "id": "step_1",
          "content": "1  Start with the..."
        },
        {
          "type": "token",
          "id": "step_2",
          "content": "2  Apply the weigh..."
        },
        {
          "type": "token",
          "id": "step_3",
          "content": "3  Add everything..."
        },
        {
          "type": "token",
          "id": "step_4",
          "content": "4  Pass through Re..."
        },
        {
          "type": "token",
          "id": "step_5",
          "content": "5  Turn scores int..."
        }
      ],
      "layout": {
        "type": "carousel",
        "gap": "large",
        "direction": "horizontal",
        "align": "center",
        "curve": 12.0
      }
    }
  ],
  "scenes": [
    {
      "id": "beat_01",
      "duration": "15s",
      "layout": "center",
      "template": "one-column",
      "narration": "Let's start with one concrete input vector. Two values come in, and each one is just raw signal waiting to be weighted.",
      "objects": [
        {
          "type": "text",
          "id": "visual_heading",
          "content": "Start with the signal",
          "style": "heading"
        },
        {
          "type": "connector",
          "id": "visual_source_link",
          "from": "visual_source_token",
          "to": "visual_focus_card"
        },
        {
          "type": "connector",
          "id": "visual_result_link",
          "from": "visual_focus_card",
          "to": "visual_result_token"
        },
        {
          "type": "group",
          "id": "visual_panel",
          "children": [
            {
              "type": "token",
              "id": "visual_stage_badge",
              "content": "Beat 1"
            },
            {
              "type": "group",
              "id": "visual_lane",
              "children": [
                {
                  "type": "group",
                  "id": "visual_source_group",
                  "label": "Signal In",
                  "children": [
                    {
                      "type": "token",
                      "id": "visual_source_token",
                      "content": "Forward Propagati..."
                    }
                  ],
                  "layout": {
                    "type": "stack",
                    "gap": "small",
                    "direction": "horizontal",
                    "align": "center"
                  }
                },
                {
                  "type": "group",
                  "id": "visual_focus_group",
                  "label": "Active Idea",
                  "children": [
                    {
                      "type": "box",
                      "id": "visual_focus_card",
                      "content": "Start with the signal",
                      "style": "accent"
                    }
                  ],
                  "layout": {
                    "type": "stack",
                    "gap": "small",
                    "direction": "horizontal",
                    "align": "center"
                  }
                },
                {
                  "type": "group",
                  "id": "visual_result_group",
                  "label": "Result",
                  "children": [
                    {
                      "type": "token",
                      "id": "visual_result_token",
                      "content": "Apply the weights"
                    }
                  ],
                  "layout": {
                    "type": "stack",
                    "gap": "small",
                    "direction": "horizontal",
                    "align": "center"
                  }
                }
              ],
              "layout": {
                "type": "flow",
                "gap": "large",
                "direction": "horizontal",
                "align": "center"
              }
            }
          ],
          "layout": {
            "type": "stack",
            "gap": "large",
            "direction": "horizontal",
            "align": "center"
          }
        }
      ],
      "animations": [
        {
          "action": "fade-in",
          "target": "visual_heading",
          "at": "0s",
          "duration": "1.2s",
          "easing": "ease-in-out"
        },
        {
          "action": "fade-in",
          "target": "visual_panel",
          "at": "0.12s",
          "duration": "1.2s",
          "easing": "ease-in-out"
        },
        {
          "action": "fade-in",
          "target": "visual_stage_badge",
          "at": "0.24s",
          "duration": "1.2s",
          "easing": "ease-in-out"
        },
        {
          "action": "fade-in",
          "target": "visual_lane",
          "at": "0.36s",
          "duration": "1.2s",
          "easing": "ease-in-out"
        },
        {
          "action": "fade-in",
          "target": "visual_source_group",
          "at": "0.48s",
          "duration": "1.2s",
          "easing": "ease-in-out"
        },
        {
          "action": "fade-in",
          "target": "visual_source_token",
          "at": "0.6s",
          "duration": "1.2s",
          "easing": "ease-in-out"
        },
        {
          "action": "fade-in",
          "target": "visual_focus_group",
          "at": "0.72s",
          "duration": "1.2s",
          "easing": "ease-in-out"
        },
        {
          "action": "fade-in",
          "target": "visual_focus_card",
          "at": "0.84s",
          "duration": "1.2s",
          "easing": "ease-in-out"
        },
        {
          "action": "fade-in",
          "target": "visual_result_group",
          "at": "0.96s",
          "duration": "1.2s",
          "easing": "ease-in-out"
        },
        {
          "action": "fade-in",
          "target": "visual_result_token",
          "at": "1.08s",
          "duration": "1.2s",
          "easing": "ease-in-out"
        },
        {
          "action": "highlight",
          "target": "visual_focus_card",
          "at": "0.4s",
          "duration": "2.8s",
          "easing": "ease-in-out",
          "style": "glow",
          "color": "accent"
        },
        {
          "action": "highlight",
          "target": "step_1",
          "at": "0s",
          "duration": "14.6s",
          "easing": "ease-in-out",
          "style": "glow",
          "color": "accent"
        },
        {
          "action": "scale",
          "target": "step_1",
          "at": "0.1s",
          "duration": "1.2s",
          "easing": "ease-in-out",
          "scale_factor": 1.14
        },
        {
          "action": "draw",
          "target": "visual_source_link",
          "at": "0.2s",
          "duration": "1.3s",
          "easing": "ease-in-out"
        },
        {
          "action": "draw",
          "target": "visual_result_link",
          "at": "0.65s",
          "duration": "1.3s",
          "easing": "ease-in-out"
        },
        {
          "action": "pulse",
          "target": "visual_source_token",
          "at": "0.2s",
          "duration": "2.8s",
          "easing": "ease-in-out",
          "color": "accent"
        },
        {
          "action": "pulse",
          "target": "visual_result_token",
          "at": "2.1s",
          "duration": "2.8s",
          "easing": "ease-in-out",
          "color": "success"
        }
      ],
      "auto_visible": false,
      "focus": "visual_focus_card",
      "focus_style": {
        "at": "0.45s",
        "duration": "1.4s",
        "scale": 1.1,
        "color": "accent",
        "style": "glow"
      },
      "camera_animations": []
    },
    {
      "id": "beat_02",
      "duration": "13s",
      "layout": "center",
      "template": "one-column",
      "narration": "Now each input gets multiplied by a learned weight. That's the network asking how strongly each input should matter.",
      "objects": [
        {
          "type": "text",
          "id": "visual_heading",
          "content": "Apply the weights",
          "style": "heading"
        },
        {
          "type": "connector",
          "id": "visual_source_link",
          "from": "visual_source_token",
          "to": "visual_focus_card"
        },
        {
          "type": "connector",
          "id": "visual_result_link",
          "from": "visual_focus_card",
          "to": "visual_result_token"
        },
        {
          "type": "group",
          "id": "visual_panel",
          "children": [
            {
              "type": "token",
              "id": "visual_stage_badge",
              "content": "Beat 2"
            },
            {
              "type": "group",
              "id": "visual_lane",
              "children": [
                {
                  "type": "group",
                  "id": "visual_source_group",
                  "label": "Signal In",
                  "children": [
                    {
                      "type": "token",
                      "id": "visual_source_token",
                      "content": "Start with the si..."
                    }
                  ],
                  "layout": {
                    "type": "stack",
                    "gap": "small",
                    "direction": "horizontal",
                    "align": "center"
                  }
                },
                {
                  "type": "group",
                  "id": "visual_focus_group",
                  "label": "Active Idea",
                  "children": [
                    {
                      "type": "box",
                      "id": "visual_focus_card",
                      "content": "Apply the weights",
                      "style": "accent"
                    }
                  ],
                  "layout": {
                    "type": "stack",
                    "gap": "small",
                    "direction": "horizontal",
                    "align": "center"
                  }
                },
                {
                  "type": "group",
                  "id": "visual_result_group",
                  "label": "Result",
                  "children": [
                    {
                      "type": "token",
                      "id": "visual_result_token",
                      "content": "Add everything to..."
                    }
                  ],
                  "layout": {
                    "type": "stack",
                    "gap": "small",
                    "direction": "horizontal",
                    "align": "center"
                  }
                }
              ],
              "layout": {
                "type": "flow",
                "gap": "large",
                "direction": "horizontal",
                "align": "center"
              }
            }
          ],
          "layout": {
            "type": "stack",
            "gap": "large",
            "direction": "horizontal",
            "align": "center"
          }
        }
      ],
      "animations": [
        {
          "action": "fade-in",
          "target": "visual_heading",
          "at": "0s",
          "duration": "1.2s",
          "easing": "ease-in-out"
        },
        {
          "action": "fade-in",
          "target": "visual_panel",
          "at": "0.12s",
          "duration": "1.2s",
          "easing": "ease-in-out"
        },
        {
          "action": "fade-in",
          "target": "visual_stage_badge",
          "at": "0.24s",
          "duration": "1.2s",
          "easing": "ease-in-out"
        },
        {
          "action": "fade-in",
          "target": "visual_lane",
          "at": "0.36s",
          "duration": "1.2s",
          "easing": "ease-in-out"
        },
        {
          "action": "fade-in",
          "target": "visual_source_group",
          "at": "0.48s",
          "duration": "1.2s",
          "easing": "ease-in-out"
        },
        {
          "action": "fade-in",
          "target": "visual_source_token",
          "at": "0.6s",
          "duration": "1.2s",
          "easing": "ease-in-out"
        },
        {
          "action": "fade-in",
          "target": "visual_focus_group",
          "at": "0.72s",
          "duration": "1.2s",
          "easing": "ease-in-out"
        },
        {
          "action": "fade-in",
          "target": "visual_focus_card",
          "at": "0.84s",
          "duration": "1.2s",
          "easing": "ease-in-out"
        },
        {
          "action": "fade-in",
          "target": "visual_result_group",
          "at": "0.96s",
          "duration": "1.2s",
          "easing": "ease-in-out"
        },
        {
          "action": "fade-in",
          "target": "visual_result_token",
          "at": "1.08s",
          "duration": "1.2s",
          "easing": "ease-in-out"
        },
        {
          "action": "highlight",
          "target": "visual_focus_card",
          "at": "0.4s",
          "duration": "2.8s",
          "easing": "ease-in-out",
          "style": "glow",
          "color": "accent"
        },
        {
          "action": "highlight",
          "target": "step_2",
          "at": "0s",
          "duration": "12.6s",
          "easing": "ease-in-out",
          "style": "glow",
          "color": "accent"
        },
        {
          "action": "scale",
          "target": "step_2",
          "at": "0.1s",
          "duration": "1.2s",
          "easing": "ease-in-out",
          "scale_factor": 1.14
        },
        {
          "action": "draw",
          "target": "visual_source_link",
          "at": "0.2s",
          "duration": "1.3s",
          "easing": "ease-in-out"
        },
        {
          "action": "draw",
          "target": "visual_result_link",
          "at": "0.65s",
          "duration": "1.3s",
          "easing": "ease-in-out"
        },
        {
          "action": "pulse",
          "target": "visual_source_token",
          "at": "0.2s",
          "duration": "2.8s",
          "easing": "ease-in-out",
          "color": "accent"
        },
        {
          "action": "pulse",
          "target": "visual_result_token",
          "at": "2.1s",
          "duration": "2.8s",
          "easing": "ease-in-out",
          "color": "success"
        }
      ],
      "auto_visible": false,
      "focus": "visual_focus_card",
      "focus_style": {
        "at": "0.45s",
        "duration": "1.4s",
        "scale": 1.1,
        "color": "accent",
        "style": "glow"
      },
      "camera_animations": []
    },
    {
      "id": "beat_03",
      "duration": "13s",
      "layout": "center",
      "template": "one-column",
      "narration": "Next we add those weighted pieces and include a bias term. That gives this neuron its pre-activation score.",
      "objects": [
        {
          "type": "text",
          "id": "visual_heading",
          "content": "Add everything together",
          "style": "heading"
        },
        {
          "type": "connector",
          "id": "visual_source_link",
          "from": "visual_source_token",
          "to": "visual_focus_card"
        },
        {
          "type": "connector",
          "id": "visual_result_link",
          "from": "visual_focus_card",
          "to": "visual_result_token"
        },
        {
          "type": "group",
          "id": "visual_panel",
          "children": [
            {
              "type": "token",
              "id": "visual_stage_badge",
              "content": "Beat 3"
            },
            {
              "type": "group",
              "id": "visual_lane",
              "children": [
                {
                  "type": "group",
                  "id": "visual_source_group",
                  "label": "Signal In",
                  "children": [
                    {
                      "type": "token",
                      "id": "visual_source_token",
                      "content": "Apply the weights"
                    }
                  ],
                  "layout": {
                    "type": "stack",
                    "gap": "small",
                    "direction": "horizontal",
                    "align": "center"
                  }
                },
                {
                  "type": "group",
                  "id": "visual_focus_group",
                  "label": "Active Idea",
                  "children": [
                    {
                      "type": "box",
                      "id": "visual_focus_card",
                      "content": "Add everything together",
                      "style": "accent"
                    }
                  ],
                  "layout": {
                    "type": "stack",
                    "gap": "small",
                    "direction": "horizontal",
                    "align": "center"
                  }
                },
                {
                  "type": "group",
                  "id": "visual_result_group",
                  "label": "Result",
                  "children": [
                    {
                      "type": "token",
                      "id": "visual_result_token",
                      "content": "Pass through ReLU"
                    }
                  ],
                  "layout": {
                    "type": "stack",
                    "gap": "small",
                    "direction": "horizontal",
                    "align": "center"
                  }
                }
              ],
              "layout": {
                "type": "flow",
                "gap": "large",
                "direction": "horizontal",
                "align": "center"
              }
            }
          ],
          "layout": {
            "type": "stack",
            "gap": "large",
            "direction": "horizontal",
            "align": "center"
          }
        }
      ],
      "animations": [
        {
          "action": "fade-in",
          "target": "visual_heading",
          "at": "0s",
          "duration": "1.2s",
          "easing": "ease-in-out"
        },
        {
          "action": "fade-in",
          "target": "visual_panel",
          "at": "0.12s",
          "duration": "1.2s",
          "easing": "ease-in-out"
        },
        {
          "action": "fade-in",
          "target": "visual_stage_badge",
          "at": "0.24s",
          "duration": "1.2s",
          "easing": "ease-in-out"
        },
        {
          "action": "fade-in",
          "target": "visual_lane",
          "at": "0.36s",
          "duration": "1.2s",
          "easing": "ease-in-out"
        },
        {
          "action": "fade-in",
          "target": "visual_source_group",
          "at": "0.48s",
          "duration": "1.2s",
          "easing": "ease-in-out"
        },
        {
          "action": "fade-in",
          "target": "visual_source_token",
          "at": "0.6s",
          "duration": "1.2s",
          "easing": "ease-in-out"
        },
        {
          "action": "fade-in",
          "target": "visual_focus_group",
          "at": "0.72s",
          "duration": "1.2s",
          "easing": "ease-in-out"
        },
        {
          "action": "fade-in",
          "target": "visual_focus_card",
          "at": "0.84s",
          "duration": "1.2s",
          "easing": "ease-in-out"
        },
        {
          "action": "fade-in",
          "target": "visual_result_group",
          "at": "0.96s",
          "duration": "1.2s",
          "easing": "ease-in-out"
        },
        {
          "action": "fade-in",
          "target": "visual_result_token",
          "at": "1.08s",
          "duration": "1.2s",
          "easing": "ease-in-out"
        },
        {
          "action": "highlight",
          "target": "visual_focus_card",
          "at": "0.4s",
          "duration": "2.8s",
          "easing": "ease-in-out",
          "style": "glow",
          "color": "accent"
        },
        {
          "action": "highlight",
          "target": "step_3",
          "at": "0s",
          "duration": "12.6s",
          "easing": "ease-in-out",
          "style": "glow",
          "color": "accent"
        },
        {
          "action": "scale",
          "target": "step_3",
          "at": "0.1s",
          "duration": "1.2s",
          "easing": "ease-in-out",
          "scale_factor": 1.14
        },
        {
          "action": "draw",
          "target": "visual_source_link",
          "at": "0.2s",
          "duration": "1.3s",
          "easing": "ease-in-out"
        },
        {
          "action": "draw",
          "target": "visual_result_link",
          "at": "0.65s",
          "duration": "1.3s",
          "easing": "ease-in-out"
        },
        {
          "action": "pulse",
          "target": "visual_source_token",
          "at": "0.2s",
          "duration": "2.8s",
          "easing": "ease-in-out",
          "color": "accent"
        },
        {
          "action": "pulse",
          "target": "visual_result_token",
          "at": "2.1s",
          "duration": "2.8s",
          "easing": "ease-in-out",
          "color": "success"
        }
      ],
      "auto_visible": false,
      "focus": "visual_focus_card",
      "focus_style": {
        "at": "0.45s",
        "duration": "1.4s",
        "scale": 1.1,
        "color": "accent",
        "style": "glow"
      },
      "camera_animations": []
    },
    {
      "id": "beat_04",
      "duration": "14s",
      "layout": "center",
      "template": "one-column",
      "narration": "If that score is negative, ReLU clamps it to zero. If it's positive, it passes through unchanged, so the neuron stays active.",
      "objects": [
        {
          "type": "text",
          "id": "visual_heading",
          "content": "Pass through ReLU",
          "style": "heading"
        },
        {
          "type": "connector",
          "id": "visual_source_link",
          "from": "visual_source_token",
          "to": "visual_focus_card"
        },
        {
          "type": "connector",
          "id": "visual_result_link",
          "from": "visual_focus_card",
          "to": "visual_result_token"
        },
        {
          "type": "group",
          "id": "visual_panel",
          "children": [
            {
              "type": "token",
              "id": "visual_stage_badge",
              "content": "Beat 4"
            },
            {
              "type": "group",
              "id": "visual_lane",
              "children": [
                {
                  "type": "group",
                  "id": "visual_source_group",
                  "label": "Signal In",
                  "children": [
                    {
                      "type": "token",
                      "id": "visual_source_token",
                      "content": "Add everything to..."
                    }
                  ],
                  "layout": {
                    "type": "stack",
                    "gap": "small",
                    "direction": "horizontal",
                    "align": "center"
                  }
                },
                {
                  "type": "group",
                  "id": "visual_focus_group",
                  "label": "Active Idea",
                  "children": [
                    {
                      "type": "box",
                      "id": "visual_focus_card",
                      "content": "Pass through ReLU",
                      "style": "accent"
                    }
                  ],
                  "layout": {
                    "type": "stack",
                    "gap": "small",
                    "direction": "horizontal",
                    "align": "center"
                  }
                },
                {
                  "type": "group",
                  "id": "visual_result_group",
                  "label": "Result",
                  "children": [
                    {
                      "type": "token",
                      "id": "visual_result_token",
                      "content": "Turn scores into..."
                    }
                  ],
                  "layout": {
                    "type": "stack",
                    "gap": "small",
                    "direction": "horizontal",
                    "align": "center"
                  }
                }
              ],
              "layout": {
                "type": "flow",
                "gap": "large",
                "direction": "horizontal",
                "align": "center"
              }
            }
          ],
          "layout": {
            "type": "stack",
            "gap": "large",
            "direction": "horizontal",
            "align": "center"
          }
        }
      ],
      "animations": [
        {
          "action": "fade-in",
          "target": "visual_heading",
          "at": "0s",
          "duration": "1.2s",
          "easing": "ease-in-out"
        },
        {
          "action": "fade-in",
          "target": "visual_panel",
          "at": "0.12s",
          "duration": "1.2s",
          "easing": "ease-in-out"
        },
        {
          "action": "fade-in",
          "target": "visual_stage_badge",
          "at": "0.24s",
          "duration": "1.2s",
          "easing": "ease-in-out"
        },
        {
          "action": "fade-in",
          "target": "visual_lane",
          "at": "0.36s",
          "duration": "1.2s",
          "easing": "ease-in-out"
        },
        {
          "action": "fade-in",
          "target": "visual_source_group",
          "at": "0.48s",
          "duration": "1.2s",
          "easing": "ease-in-out"
        },
        {
          "action": "fade-in",
          "target": "visual_source_token",
          "at": "0.6s",
          "duration": "1.2s",
          "easing": "ease-in-out"
        },
        {
          "action": "fade-in",
          "target": "visual_focus_group",
          "at": "0.72s",
          "duration": "1.2s",
          "easing": "ease-in-out"
        },
        {
          "action": "fade-in",
          "target": "visual_focus_card",
          "at": "0.84s",
          "duration": "1.2s",
          "easing": "ease-in-out"
        },
        {
          "action": "fade-in",
          "target": "visual_result_group",
          "at": "0.96s",
          "duration": "1.2s",
          "easing": "ease-in-out"
        },
        {
          "action": "fade-in",
          "target": "visual_result_token",
          "at": "1.08s",
          "duration": "1.2s",
          "easing": "ease-in-out"
        },
        {
          "action": "highlight",
          "target": "visual_focus_card",
          "at": "0.4s",
          "duration": "2.8s",
          "easing": "ease-in-out",
          "style": "glow",
          "color": "accent"
        },
        {
          "action": "highlight",
          "target": "step_4",
          "at": "0s",
          "duration": "13.6s",
          "easing": "ease-in-out",
          "style": "glow",
          "color": "accent"
        },
        {
          "action": "scale",
          "target": "step_4",
          "at": "0.1s",
          "duration": "1.2s",
          "easing": "ease-in-out",
          "scale_factor": 1.14
        },
        {
          "action": "draw",
          "target": "visual_source_link",
          "at": "0.2s",
          "duration": "1.3s",
          "easing": "ease-in-out"
        },
        {
          "action": "draw",
          "target": "visual_result_link",
          "at": "0.65s",
          "duration": "1.3s",
          "easing": "ease-in-out"
        },
        {
          "action": "pulse",
          "target": "visual_source_token",
          "at": "0.2s",
          "duration": "2.8s",
          "easing": "ease-in-out",
          "color": "accent"
        },
        {
          "action": "pulse",
          "target": "visual_result_token",
          "at": "2.1s",
          "duration": "2.8s",
          "easing": "ease-in-out",
          "color": "success"
        }
      ],
      "auto_visible": false,
      "focus": "visual_focus_card",
      "focus_style": {
        "at": "0.45s",
        "duration": "1.4s",
        "scale": 1.1,
        "color": "accent",
        "style": "glow"
      },
      "camera_animations": []
    },
    {
      "id": "beat_05",
      "duration": "15s",
      "layout": "center",
      "template": "one-column",
      "narration": "At the output layer, the scores are compared and turned into probabilities, so we can see which class the network believes most.",
      "objects": [
        {
          "type": "text",
          "id": "visual_heading",
          "content": "Turn scores into a predic...",
          "style": "heading"
        },
        {
          "type": "connector",
          "id": "visual_source_link",
          "from": "visual_source_token",
          "to": "visual_focus_card"
        },
        {
          "type": "connector",
          "id": "visual_result_link",
          "from": "visual_focus_card",
          "to": "visual_result_token"
        },
        {
          "type": "group",
          "id": "visual_panel",
          "children": [
            {
              "type": "token",
              "id": "visual_stage_badge",
              "content": "Beat 5"
            },
            {
              "type": "group",
              "id": "visual_lane",
              "children": [
                {
                  "type": "group",
                  "id": "visual_source_group",
                  "label": "Signal In",
                  "children": [
                    {
                      "type": "token",
                      "id": "visual_source_token",
                      "content": "Pass through ReLU"
                    }
                  ],
                  "layout": {
                    "type": "stack",
                    "gap": "small",
                    "direction": "horizontal",
                    "align": "center"
                  }
                },
                {
                  "type": "group",
                  "id": "visual_focus_group",
                  "label": "Active Idea",
                  "children": [
                    {
                      "type": "box",
                      "id": "visual_focus_card",
                      "content": "Turn scores into a pred...",
                      "style": "accent"
                    }
                  ],
                  "layout": {
                    "type": "stack",
                    "gap": "small",
                    "direction": "horizontal",
                    "align": "center"
                  }
                },
                {
                  "type": "group",
                  "id": "visual_result_group",
                  "label": "Result",
                  "children": [
                    {
                      "type": "token",
                      "id": "visual_result_token",
                      "content": "Takeaway"
                    }
                  ],
                  "layout": {
                    "type": "stack",
                    "gap": "small",
                    "direction": "horizontal",
                    "align": "center"
                  }
                }
              ],
              "layout": {
                "type": "flow",
                "gap": "large",
                "direction": "horizontal",
                "align": "center"
              }
            }
          ],
          "layout": {
            "type": "stack",
            "gap": "large",
            "direction": "horizontal",
            "align": "center"
          }
        }
      ],
      "animations": [
        {
          "action": "fade-in",
          "target": "visual_heading",
          "at": "0s",
          "duration": "1.2s",
          "easing": "ease-in-out"
        },
        {
          "action": "fade-in",
          "target": "visual_panel",
          "at": "0.12s",
          "duration": "1.2s",
          "easing": "ease-in-out"
        },
        {
          "action": "fade-in",
          "target": "visual_stage_badge",
          "at": "0.24s",
          "duration": "1.2s",
          "easing": "ease-in-out"
        },
        {
          "action": "fade-in",
          "target": "visual_lane",
          "at": "0.36s",
          "duration": "1.2s",
          "easing": "ease-in-out"
        },
        {
          "action": "fade-in",
          "target": "visual_source_group",
          "at": "0.48s",
          "duration": "1.2s",
          "easing": "ease-in-out"
        },
        {
          "action": "fade-in",
          "target": "visual_source_token",
          "at": "0.6s",
          "duration": "1.2s",
          "easing": "ease-in-out"
        },
        {
          "action": "fade-in",
          "target": "visual_focus_group",
          "at": "0.72s",
          "duration": "1.2s",
          "easing": "ease-in-out"
        },
        {
          "action": "fade-in",
          "target": "visual_focus_card",
          "at": "0.84s",
          "duration": "1.2s",
          "easing": "ease-in-out"
        },
        {
          "action": "fade-in",
          "target": "visual_result_group",
          "at": "0.96s",
          "duration": "1.2s",
          "easing": "ease-in-out"
        },
        {
          "action": "fade-in",
          "target": "visual_result_token",
          "at": "1.08s",
          "duration": "1.2s",
          "easing": "ease-in-out"
        },
        {
          "action": "highlight",
          "target": "visual_focus_card",
          "at": "0.4s",
          "duration": "2.8s",
          "easing": "ease-in-out",
          "style": "glow",
          "color": "accent"
        },
        {
          "action": "highlight",
          "target": "step_5",
          "at": "0s",
          "duration": "14.6s",
          "easing": "ease-in-out",
          "style": "glow",
          "color": "accent"
        },
        {
          "action": "scale",
          "target": "step_5",
          "at": "0.1s",
          "duration": "1.2s",
          "easing": "ease-in-out",
          "scale_factor": 1.14
        },
        {
          "action": "draw",
          "target": "visual_source_link",
          "at": "0.2s",
          "duration": "1.3s",
          "easing": "ease-in-out"
        },
        {
          "action": "draw",
          "target": "visual_result_link",
          "at": "0.65s",
          "duration": "1.3s",
          "easing": "ease-in-out"
        },
        {
          "action": "pulse",
          "target": "visual_source_token",
          "at": "0.2s",
          "duration": "2.8s",
          "easing": "ease-in-out",
          "color": "accent"
        },
        {
          "action": "pulse",
          "target": "visual_result_token",
          "at": "2.1s",
          "duration": "2.8s",
          "easing": "ease-in-out",
          "color": "success"
        }
      ],
      "auto_visible": false,
      "focus": "visual_focus_card",
      "focus_style": {
        "at": "0.45s",
        "duration": "1.4s",
        "scale": 1.1,
        "color": "accent",
        "style": "glow"
      },
      "camera_animations": []
    }
  ]
}
